xdggs_dggrid4py/IGEO7.py
xdggs_dggrid4py/regridding.py
xdggs_dggrid4py/regridding_methods/__init__.py
xdggs_dggrid4py/regridding_methods/centerpoint.py
xdggs_dggrid4py/regridding_methods/nearestpoint.py
xdggs_dggrid4py/utils.py
xdggs_dggrid4py-0.1.3.dist-info/LICENSE
xdggs_dggrid4py-0.1.3.dist-info/METADATA
xdggs_dggrid4py-0.1.3.dist-info/WHEEL
xdggs_dggrid4py-0.1.3.dist-info/RECORD
