Metadata-Version: 2.3
Name: xdggs-dggrid4py
Version: 0.1.3
Summary: A plugin for Xarray-xdggs that implements DGGRID as DGGS provider
Author: Wai Tik Chan
Author-email: wai.tik.chan@ut.ee
Requires-Python: >=3.10,<4.0
Classifier: Programming Language :: Python :: 3
Classifier: Programming Language :: Python :: 3.10
Classifier: Programming Language :: Python :: 3.11
Classifier: Programming Language :: Python :: 3.12
Classifier: Programming Language :: Python :: 3.13
Requires-Dist: dask (>=2025.2.0,<2026.0.0)
Requires-Dist: dggrid4py (>=0.4.1,<0.5.0)
Requires-Dist: numpy (>=1.24.1,<2.0.0)
Requires-Dist: rasterio (>=1.4.3,<2.0.0)
Requires-Dist: rioxarray (>=0.18.1,<0.19.0)
Requires-Dist: shapely (>=2.0.7,<3.0.0)
Requires-Dist: tqdm (>=4.67.1,<5.0.0)
Requires-Dist: xarray[io] (>=2025.1.2,<2026.0.0)
Requires-Dist: xdggs (>=0.2.0,<0.3.0)
Requires-Dist: zarr (==2.18.3)
